README.rst
setup.py
src/j1m/__init__.py
src/j1m/sphinxautozconfig.py
src/j1m.sphinxautozconfig.egg-info/PKG-INFO
src/j1m.sphinxautozconfig.egg-info/SOURCES.txt
src/j1m.sphinxautozconfig.egg-info/dependency_links.txt
src/j1m.sphinxautozconfig.egg-info/namespace_packages.txt
src/j1m.sphinxautozconfig.egg-info/requires.txt
src/j1m.sphinxautozconfig.egg-info/top_level.txt