Metadata-Version: 1.0
Name: j1m.sphinxautozconfig
Version: 0.1.0
Summary: Spinx support for ZConfig
Home-page: UNKNOWN
Author: Jim Fulton
Author-email: jim@jimfulton.info
License: MIT
Platform: UNKNOWN
